{
  "runDate": "2024-09-06",
  "trainWindow3m": {
    "start": "2024-06-07",
    "end": "2024-09-06",
    "topCandidates": [
      {
        "strategyName": "GMOCOIN-RSI-P14-OS30-OB70-MP1-LOT0.1-H25-ATRSL3.5-ATRTP4",
        "hold": 25,
        "family": "slow",
        "atrsl": 3.5,
        "atrtp": 4,
        "totalTrades": 175,
        "winRate": 62.86,
        "grossPnl": 28,
        "totalCommission": 350,
        "netPnl": -322,
        "avgNetPnl": -1.84,
        "sharpeRatio": -0.0355,
        "maxDrawdown": -942.5,
        "profitFactor": 0.8993,
        "score": -1.84,
        "grossReturnPct": 5.6,
        "commissionPct": 70,
        "netReturnPct": -64.4,
        "maxDrawdownPct": -188.5
      },
      {
        "strategyName": "GMOCOIN-RSI-P14-OS30-OB70-MP1-LOT0.1-H30-ATRSL3.5-ATRTP4",
        "hold": 30,
        "family": "slow",
        "atrsl": 3.5,
        "atrtp": 4,
        "totalTrades": 174,
        "winRate": 63.79,
        "grossPnl": 7,
        "totalCommission": 348,
        "netPnl": -341,
        "avgNetPnl": -1.96,
        "sharpeRatio": -0.0375,
        "maxDrawdown": -1001,
        "profitFactor": 0.894,
        "score": -1.9776,
        "grossReturnPct": 1.4,
        "commissionPct": 69.6,
        "netReturnPct": -68.2,
        "maxDrawdownPct": -200.2
      },
      {
        "strategyName": "GMOCOIN-RSI-P14-OS30-OB70-MP1-LOT0.1-H25-ATRSL3.5-ATRTP3",
        "hold": 25,
        "family": "slow",
        "atrsl": 3.5,
        "atrtp": 3,
        "totalTrades": 175,
        "winRate": 62.86,
        "grossPnl": -23,
        "totalCommission": 350,
        "netPnl": -373,
        "avgNetPnl": -2.13,
        "sharpeRatio": -0.0412,
        "maxDrawdown": -966,
        "profitFactor": 0.8834,
        "score": -2.1314,
        "grossReturnPct": -4.6,
        "commissionPct": 70,
        "netReturnPct": -74.6,
        "maxDrawdownPct": -193.2
      },
      {
        "strategyName": "GMOCOIN-RSI-P14-OS30-OB70-MP1-LOT0.1-H30-ATRSL3.5-ATRTP3",
        "hold": 30,
        "family": "slow",
        "atrsl": 3.5,
        "atrtp": 3,
        "totalTrades": 174,
        "winRate": 63.79,
        "grossPnl": -44,
        "totalCommission": 348,
        "netPnl": -392,
        "avgNetPnl": -2.25,
        "sharpeRatio": -0.0432,
        "maxDrawdown": -1024.5,
        "profitFactor": 0.8781,
        "score": -2.2734,
        "grossReturnPct": -8.8,
        "commissionPct": 69.6,
        "netReturnPct": -78.4,
        "maxDrawdownPct": -204.9
      },
      {
        "strategyName": "GMOCOIN-RSI-P14-OS30-OB70-MP1-LOT0.1-H15-ATRSL3.5-ATRTP4",
        "hold": 15,
        "family": "fast",
        "atrsl": 3.5,
        "atrtp": 4,
        "totalTrades": 178,
        "winRate": 55.06,
        "grossPnl": -158,
        "totalCommission": 356,
        "netPnl": -514,
        "avgNetPnl": -2.89,
        "sharpeRatio": -0.0574,
        "maxDrawdown": -989.5,
        "profitFactor": 0.8382,
        "score": -2.5726,
        "grossReturnPct": -31.6,
        "commissionPct": 71.2,
        "netReturnPct": -102.8,
        "maxDrawdownPct": -197.9
      }
    ]
  },
  "trainWindow1m": {
    "start": "2024-08-07",
    "end": "2024-09-06",
    "topCandidates": [
      {
        "strategyName": "GMOCOIN-RSI-P14-OS30-OB70-MP1-LOT0.1-H25-ATRSL3.5-ATRTP4",
        "hold": 25,
        "family": "slow",
        "atrsl": 3.5,
        "atrtp": 4,
        "totalTrades": 57,
        "winRate": 57.89,
        "grossPnl": -433,
        "totalCommission": 114,
        "netPnl": -547,
        "avgNetPnl": -9.6,
        "sharpeRatio": -0.1495,
        "maxDrawdown": -942.5,
        "profitFactor": 0.643,
        "score": -2.8789,
        "grossReturnPct": -86.6,
        "commissionPct": 22.8,
        "netReturnPct": -109.4,
        "maxDrawdownPct": -188.5
      },
      {
        "strategyName": "GMOCOIN-RSI-P14-OS30-OB70-MP1-LOT0.1-H25-ATRSL3.5-ATRTP3",
        "hold": 25,
        "family": "slow",
        "atrsl": 3.5,
        "atrtp": 3,
        "totalTrades": 57,
        "winRate": 57.89,
        "grossPnl": -456.5,
        "totalCommission": 114,
        "netPnl": -570.5,
        "avgNetPnl": -10.01,
        "sharpeRatio": -0.1569,
        "maxDrawdown": -966,
        "profitFactor": 0.6276,
        "score": -3.0026,
        "grossReturnPct": -91.3,
        "commissionPct": 22.8,
        "netReturnPct": -114.1,
        "maxDrawdownPct": -193.2
      },
      {
        "strategyName": "GMOCOIN-RSI-P14-OS30-OB70-MP1-LOT0.1-H30-ATRSL3.5-ATRTP4",
        "hold": 30,
        "family": "slow",
        "atrsl": 3.5,
        "atrtp": 4,
        "totalTrades": 56,
        "winRate": 60.71,
        "grossPnl": -460.5,
        "totalCommission": 112,
        "netPnl": -572.5,
        "avgNetPnl": -10.22,
        "sharpeRatio": -0.157,
        "maxDrawdown": -1001,
        "profitFactor": 0.6305,
        "score": -3.1599,
        "grossReturnPct": -92.1,
        "commissionPct": 22.4,
        "netReturnPct": -114.5,
        "maxDrawdownPct": -200.2
      },
      {
        "strategyName": "GMOCOIN-RSI-P14-OS30-OB70-MP1-LOT0.1-H30-ATRSL3.5-ATRTP3",
        "hold": 30,
        "family": "slow",
        "atrsl": 3.5,
        "atrtp": 3,
        "totalTrades": 56,
        "winRate": 60.71,
        "grossPnl": -484,
        "totalCommission": 112,
        "netPnl": -596,
        "avgNetPnl": -10.64,
        "sharpeRatio": -0.1644,
        "maxDrawdown": -1024.5,
        "profitFactor": 0.6154,
        "score": -3.2896,
        "grossReturnPct": -96.8,
        "commissionPct": 22.4,
        "netReturnPct": -119.2,
        "maxDrawdownPct": -204.9
      },
      {
        "strategyName": "GMOCOIN-RSI-P14-OS30-OB70-MP1-LOT0.1-H25-ATRSL4-ATRTP4",
        "hold": 25,
        "family": "slow",
        "atrsl": 4,
        "atrtp": 4,
        "totalTrades": 57,
        "winRate": 57.89,
        "grossPnl": -533,
        "totalCommission": 114,
        "netPnl": -647,
        "avgNetPnl": -11.35,
        "sharpeRatio": -0.1687,
        "maxDrawdown": -1020,
        "profitFactor": 0.6036,
        "score": -3.4053,
        "grossReturnPct": -106.6,
        "commissionPct": 22.8,
        "netReturnPct": -129.4,
        "maxDrawdownPct": -204
      }
    ]
  },
  "executionWindow": {
    "start": "2024-09-07",
    "end": "2024-09-13"
  },
  "consensus": {
    "family3m": "slow",
    "family1m": "slow",
    "atrslBand3m": [
      3.5
    ],
    "atrslBand1m": [
      3.5,
      4
    ],
    "atrtpBand3m": [
      3,
      4
    ],
    "atrtpBand1m": [
      3,
      4
    ],
    "sharedAtrslBand": [
      3.5
    ],
    "sharedAtrtpBand": [
      3,
      4
    ],
    "agreementLevel": "strong"
  },
  "decision": {
    "action": "pause",
    "selectedParams": {
      "hold": 30,
      "atrsl": 3.5,
      "atrtp": 4
    },
    "reason": "both 3m and 1m top candidates are non-positive after fees"
  },
  "currentMetrics": {
    "window3m": {
      "strategyName": "GMOCOIN-RSI-P14-OS30-OB70-MP1-LOT0.1-H30-ATRSL3.5-ATRTP4",
      "hold": 30,
      "family": "slow",
      "atrsl": 3.5,
      "atrtp": 4,
      "totalTrades": 174,
      "winRate": 63.79,
      "grossPnl": 7,
      "totalCommission": 348,
      "netPnl": -341,
      "avgNetPnl": -1.96,
      "sharpeRatio": -0.0375,
      "maxDrawdown": -1001,
      "profitFactor": 0.894,
      "score": -1.9776,
      "grossReturnPct": 1.4,
      "commissionPct": 69.6,
      "netReturnPct": -68.2,
      "maxDrawdownPct": -200.2
    },
    "window1m": {
      "strategyName": "GMOCOIN-RSI-P14-OS30-OB70-MP1-LOT0.1-H30-ATRSL3.5-ATRTP4",
      "hold": 30,
      "family": "slow",
      "atrsl": 3.5,
      "atrtp": 4,
      "totalTrades": 56,
      "winRate": 60.71,
      "grossPnl": -460.5,
      "totalCommission": 112,
      "netPnl": -572.5,
      "avgNetPnl": -10.22,
      "sharpeRatio": -0.157,
      "maxDrawdown": -1001,
      "profitFactor": 0.6305,
      "score": -3.1599,
      "grossReturnPct": -92.1,
      "commissionPct": 22.4,
      "netReturnPct": -114.5,
      "maxDrawdownPct": -200.2
    }
  },
  "selectedMetrics": {
    "window3m": {
      "strategyName": "GMOCOIN-RSI-P14-OS30-OB70-MP1-LOT0.1-H30-ATRSL3.5-ATRTP4",
      "hold": 30,
      "family": "slow",
      "atrsl": 3.5,
      "atrtp": 4,
      "totalTrades": 174,
      "winRate": 63.79,
      "grossPnl": 7,
      "totalCommission": 348,
      "netPnl": -341,
      "avgNetPnl": -1.96,
      "sharpeRatio": -0.0375,
      "maxDrawdown": -1001,
      "profitFactor": 0.894,
      "score": -1.9776,
      "grossReturnPct": 1.4,
      "commissionPct": 69.6,
      "netReturnPct": -68.2,
      "maxDrawdownPct": -200.2
    },
    "window1m": {
      "strategyName": "GMOCOIN-RSI-P14-OS30-OB70-MP1-LOT0.1-H30-ATRSL3.5-ATRTP4",
      "hold": 30,
      "family": "slow",
      "atrsl": 3.5,
      "atrtp": 4,
      "totalTrades": 56,
      "winRate": 60.71,
      "grossPnl": -460.5,
      "totalCommission": 112,
      "netPnl": -572.5,
      "avgNetPnl": -10.22,
      "sharpeRatio": -0.157,
      "maxDrawdown": -1001,
      "profitFactor": 0.6305,
      "score": -3.1599,
      "grossReturnPct": -92.1,
      "commissionPct": 22.4,
      "netReturnPct": -114.5,
      "maxDrawdownPct": -200.2
    }
  },
  "validation": null,
  "validationSkippedReason": "decision is pause"
}
